[
    {
        "TOURNAMENT_CATEGORIES_FK": 598,
        "VERTEX": 3,
        "categoryOfFighting": "25",
        "countOfRounds": "2",
        "countryOfLeftFighter": "Республика Коми",
        "countryOfRightFighter": "Псковская",
        "durationOfBreak": "45",
        "durationOfRound": "60",
        "fightId": 1,
        "nameOfLeftFighter": "Лошкарев Егор",
        "nameOfRightFighter": "Гаврилов Кирилл",
        "orderUID_left": 3127,
        "orderUID_right": 3156
    },
    {
        "TOURNAMENT_CATEGORIES_FK": 598,
        "VERTEX": 2,
        "categoryOfFighting": "25",
        "countOfRounds": "2",
        "countryOfLeftFighter": "Псковская",
        "countryOfRightFighter": "Псковская",
        "durationOfBreak": "45",
        "durationOfRound": "60",
        "fightId": 2,
        "nameOfLeftFighter": "Сабурин  Игорь",
        "nameOfRightFighter": "Кучуков  Максим",
        "orderUID_left": 3155,
        "orderUID_right": 3154
    },
    {
        "TOURNAMENT_CATEGORIES_FK": 600,
        "VERTEX": 9,
        "categoryOfFighting": "32",
        "countOfRounds": "2",
        "countryOfLeftFighter": "Республика Коми",
        "countryOfRightFighter": "Псковская",
        "durationOfBreak": "45",
        "durationOfRound": "60",
        "fightId": 3,
        "nameOfLeftFighter": "Афанасьев Дмитрий",
        "nameOfRightFighter": "Коваль Семен",
        "orderUID_left": 3122,
        "orderUID_right": 3152
    },
    {
        "TOURNAMENT_CATEGORIES_FK": 600,
        "VERTEX": 8,
        "categoryOfFighting": "32",
        "countOfRounds": "2",
        "countryOfLeftFighter": "Псковская",
        "countryOfRightFighter": "Минск",
        "durationOfBreak": "45",
        "durationOfRound": "60",
        "fightId": 4,
        "nameOfLeftFighter": "Алексеев Дмитрий",
        "nameOfRightFighter": "Насковец  Вениамин",
        "orderUID_left": 3145,
        "orderUID_right": 3099
    },
    {
        "TOURNAMENT_CATEGORIES_FK": 602,
        "VERTEX": 2,
        "categoryOfFighting": "42",
        "countOfRounds": "2",
        "countryOfLeftFighter": "Москва",
        "countryOfRightFighter": "Минск",
        "durationOfBreak": "45",
        "durationOfRound": "60",
        "fightId": 5,
        "nameOfLeftFighter": "Мартиросян Арутюн",
        "nameOfRightFighter": "Цыбулька  Никита  ",
        "orderUID_left": 3198,
        "orderUID_right": 3090
    },
    {
        "TOURNAMENT_CATEGORIES_FK": 586,
        "VERTEX": 1,
        "categoryOfFighting": "28",
        "countOfRounds": "2",
        "countryOfLeftFighter": "Республика Коми",
        "countryOfRightFighter": "Минск",
        "durationOfBreak": "60",
        "durationOfRound": "120",
        "fightId": 6,
        "nameOfLeftFighter": "Рабинович Игорь",
        "nameOfRightFighter": "Гулякевич  Артём",
        "orderUID_left": 3125,
        "orderUID_right": 3084
    },
    {
        "TOURNAMENT_CATEGORIES_FK": 587,
        "VERTEX": 4,
        "categoryOfFighting": "32",
        "countOfRounds": "2",
        "countryOfLeftFighter": "Москва",
        "countryOfRightFighter": "Республика Коми",
        "durationOfBreak": "60",
        "durationOfRound": "120",
        "fightId": 7,
        "nameOfLeftFighter": "Малянов Максим",
        "nameOfRightFighter": "Горшенин Владислав",
        "orderUID_left": 3187,
        "orderUID_right": 3128
    },
    {
        "TOURNAMENT_CATEGORIES_FK": 588,
        "VERTEX": 6,
        "categoryOfFighting": "37",
        "countOfRounds": "2",
        "countryOfLeftFighter": "Москва",
        "countryOfRightFighter": "Республика Коми",
        "durationOfBreak": "60",
        "durationOfRound": "120",
        "fightId": 8,
        "nameOfLeftFighter": "Федоров Григорий",
        "nameOfRightFighter": "Винокуров Тимофей",
        "orderUID_left": 3195,
        "orderUID_right": 3123
    },
    {
        "TOURNAMENT_CATEGORIES_FK": 588,
        "VERTEX": 5,
        "categoryOfFighting": "37",
        "countOfRounds": "2",
        "countryOfLeftFighter": "Москва",
        "countryOfRightFighter": "Республика Коми",
        "durationOfBreak": "60",
        "durationOfRound": "120",
        "fightId": 9,
        "nameOfLeftFighter": "Моцак Иван",
        "nameOfRightFighter": "Деркизенов Рустам",
        "orderUID_left": 3192,
        "orderUID_right": 3120
    },
    {
        "TOURNAMENT_CATEGORIES_FK": 588,
        "VERTEX": 4,
        "categoryOfFighting": "37",
        "countOfRounds": "2",
        "countryOfLeftFighter": "Псковская",
        "countryOfRightFighter": "Минск",
        "durationOfBreak": "60",
        "durationOfRound": "120",
        "fightId": 10,
        "nameOfLeftFighter": "Лукьянов  Евгений",
        "nameOfRightFighter": "Литвинчик  Алексей ",
        "orderUID_left": 3157,
        "orderUID_right": 3087
    },
    {
        "TOURNAMENT_CATEGORIES_FK": 595,
        "VERTEX": 1,
        "categoryOfFighting": "42",
        "countOfRounds": "2",
        "countryOfLeftFighter": "Москва",
        "countryOfRightFighter": "Минск",
        "durationOfBreak": "60",
        "durationOfRound": "120",
        "fightId": 11,
        "nameOfLeftFighter": "Трощенкова Виктория",
        "nameOfRightFighter": "Миненкова Дарья",
        "orderUID_left": 3191,
        "orderUID_right": 3114
    },
    {
        "TOURNAMENT_CATEGORIES_FK": 589,
        "VERTEX": 3,
        "categoryOfFighting": "42",
        "countOfRounds": "2",
        "countryOfLeftFighter": "Республика Коми",
        "countryOfRightFighter": "Псковская",
        "durationOfBreak": "60",
        "durationOfRound": "120",
        "fightId": 12,
        "nameOfLeftFighter": "Вагапов Вадим",
        "nameOfRightFighter": "Малеев  Михаил",
        "orderUID_left": 3126,
        "orderUID_right": 3149
    },
    {
        "TOURNAMENT_CATEGORIES_FK": 589,
        "VERTEX": 2,
        "categoryOfFighting": "42",
        "countOfRounds": "2",
        "countryOfLeftFighter": "Республика Коми",
        "countryOfRightFighter": "Минск",
        "durationOfBreak": "60",
        "durationOfRound": "120",
        "fightId": 13,
        "nameOfLeftFighter": "Логинов Константин",
        "nameOfRightFighter": "Малахов  Михаил      ",
        "orderUID_left": 3118,
        "orderUID_right": 3089
    },
    {
        "TOURNAMENT_CATEGORIES_FK": 590,
        "VERTEX": 5,
        "categoryOfFighting": "47",
        "countOfRounds": "2",
        "countryOfLeftFighter": "Республика Коми",
        "countryOfRightFighter": "Псковская",
        "durationOfBreak": "60",
        "durationOfRound": "120",
        "fightId": 14,
        "nameOfLeftFighter": "Семёнов Максим",
        "nameOfRightFighter": "Анискович  Никита",
        "orderUID_left": 3119,
        "orderUID_right": 3142
    },
    {
        "TOURNAMENT_CATEGORIES_FK": 590,
        "VERTEX": 4,
        "categoryOfFighting": "47",
        "countOfRounds": "2",
        "countryOfLeftFighter": "Псковская",
        "countryOfRightFighter": "Минск",
        "durationOfBreak": "60",
        "durationOfRound": "120",
        "fightId": 15,
        "nameOfLeftFighter": "Конярский Кирилл",
        "nameOfRightFighter": "Суздалев  Роман",
        "orderUID_left": 3141,
        "orderUID_right": 3075
    },
    {
        "TOURNAMENT_CATEGORIES_FK": 591,
        "VERTEX": 4,
        "categoryOfFighting": "100000",
        "countOfRounds": "2",
        "countryOfLeftFighter": "Республика Коми",
        "countryOfRightFighter": "Псковская",
        "durationOfBreak": "60",
        "durationOfRound": "120",
        "fightId": 16,
        "nameOfLeftFighter": "Новиков Данила",
        "nameOfRightFighter": "Огородник Артем",
        "orderUID_left": 3124,
        "orderUID_right": 3178
    },
    {
        "TOURNAMENT_CATEGORIES_FK": 526,
        "VERTEX": 1,
        "categoryOfFighting": "48",
        "countOfRounds": "3",
        "countryOfLeftFighter": "Москва",
        "countryOfRightFighter": "Псковская",
        "durationOfBreak": "60",
        "durationOfRound": "90",
        "fightId": 17,
        "nameOfLeftFighter": "Федоров Владимир",
        "nameOfRightFighter": "Прошенков Владислав",
        "orderUID_left": 3196,
        "orderUID_right": 3168
    },
    {
        "TOURNAMENT_CATEGORIES_FK": 539,
        "VERTEX": 2,
        "categoryOfFighting": "52",
        "countOfRounds": "3",
        "countryOfLeftFighter": "Калининградская",
        "countryOfRightFighter": "Москва",
        "durationOfBreak": "60",
        "durationOfRound": "90",
        "fightId": 18,
        "nameOfLeftFighter": "Николаева Элеонора",
        "nameOfRightFighter": "Шарифьянова  Анастасия",
        "orderUID_left": 3115,
        "orderUID_right": 3194
    },
    {
        "TOURNAMENT_CATEGORIES_FK": 529,
        "VERTEX": 3,
        "categoryOfFighting": "57",
        "countOfRounds": "3",
        "countryOfLeftFighter": "Республика Коми",
        "countryOfRightFighter": "Минск",
        "durationOfBreak": "60",
        "durationOfRound": "90",
        "fightId": 19,
        "nameOfLeftFighter": "Погребницкий Илья",
        "nameOfRightFighter": "Свирик  Егор",
        "orderUID_left": 3199,
        "orderUID_right": 3107
    },
    {
        "TOURNAMENT_CATEGORIES_FK": 529,
        "VERTEX": 2,
        "categoryOfFighting": "57",
        "countOfRounds": "3",
        "countryOfLeftFighter": "Республика Коми",
        "countryOfRightFighter": "Республика Коми",
        "durationOfBreak": "60",
        "durationOfRound": "90",
        "fightId": 20,
        "nameOfLeftFighter": "Игнатов Станислав",
        "nameOfRightFighter": "Шаков Михаил",
        "orderUID_left": 3130,
        "orderUID_right": 3121
    },
    {
        "TOURNAMENT_CATEGORIES_FK": 532,
        "VERTEX": 1,
        "categoryOfFighting": "66",
        "countOfRounds": "3",
        "countryOfLeftFighter": "Республика Коми",
        "countryOfRightFighter": "Псковская",
        "durationOfBreak": "60",
        "durationOfRound": "90",
        "fightId": 21,
        "nameOfLeftFighter": "Гричкуновский Никита",
        "nameOfRightFighter": "Шведченко  Даниил",
        "orderUID_left": 3117,
        "orderUID_right": 3179
    },
    {
        "TOURNAMENT_CATEGORIES_FK": 573,
        "VERTEX": 1,
        "categoryOfFighting": "42",
        "countOfRounds": "2",
        "countryOfLeftFighter": "Республика Коми",
        "countryOfRightFighter": "Минск",
        "durationOfBreak": "60",
        "durationOfRound": "120",
        "fightId": 22,
        "nameOfLeftFighter": "Пигулин Никита",
        "nameOfRightFighter": "Бобровский  Сергей",
        "orderUID_left": 3116,
        "orderUID_right": 3078
    },
    {
        "TOURNAMENT_CATEGORIES_FK": 582,
        "VERTEX": 2,
        "categoryOfFighting": "50",
        "countOfRounds": "2",
        "countryOfLeftFighter": "Москва",
        "countryOfRightFighter": "Минск",
        "durationOfBreak": "60",
        "durationOfRound": "90",
        "fightId": 23,
        "nameOfLeftFighter": "Лялина Светлана",
        "nameOfRightFighter": "Почицкая  Мария    ",
        "orderUID_left": 3193,
        "orderUID_right": 3091
    },
    {
        "TOURNAMENT_CATEGORIES_FK": 576,
        "VERTEX": 2,
        "categoryOfFighting": "57",
        "countOfRounds": "2",
        "countryOfLeftFighter": "Республика Коми",
        "countryOfRightFighter": "Минск",
        "durationOfBreak": "60",
        "durationOfRound": "120",
        "fightId": 24,
        "nameOfLeftFighter": "Игнатов Станислав",
        "nameOfRightFighter": "Белонович  Ярослав",
        "orderUID_left": 3131,
        "orderUID_right": 3081
    },
    {
        "TOURNAMENT_CATEGORIES_FK": 577,
        "VERTEX": 1,
        "categoryOfFighting": "63",
        "countOfRounds": "2",
        "countryOfLeftFighter": "Республика Коми",
        "countryOfRightFighter": "Минск",
        "durationOfBreak": "60",
        "durationOfRound": "120",
        "fightId": 25,
        "nameOfLeftFighter": "Гуляев Тимофей",
        "nameOfRightFighter": "Заблоцкий  Павел",
        "orderUID_left": 3135,
        "orderUID_right": 3092
    },
    {
        "TOURNAMENT_CATEGORIES_FK": 578,
        "VERTEX": 1,
        "categoryOfFighting": "69",
        "countOfRounds": "2",
        "countryOfLeftFighter": "Минск",
        "countryOfRightFighter": "Минск",
        "durationOfBreak": "60",
        "durationOfRound": "120",
        "fightId": 26,
        "nameOfLeftFighter": "Данько  Андрей",
        "nameOfRightFighter": "Вербило  Илья          ",
        "orderUID_left": 3113,
        "orderUID_right": 3093
    },
    {
        "TOURNAMENT_CATEGORIES_FK": 446,
        "VERTEX": 1,
        "categoryOfFighting": "51",
        "countOfRounds": "3",
        "countryOfLeftFighter": "Псковская",
        "countryOfRightFighter": "Мурманская",
        "durationOfBreak": "60",
        "durationOfRound": "90",
        "fightId": 27,
        "nameOfLeftFighter": "Лугашев Виталий",
        "nameOfRightFighter": "Вандышев Иван",
        "orderUID_left": 3169,
        "orderUID_right": 3200
    },
    {
        "TOURNAMENT_CATEGORIES_FK": 508,
        "VERTEX": 7,
        "categoryOfFighting": "63.5",
        "countOfRounds": "3",
        "countryOfLeftFighter": "Псковская",
        "countryOfRightFighter": "Рязанская",
        "durationOfBreak": "60",
        "durationOfRound": "90",
        "fightId": 28,
        "nameOfLeftFighter": "Ардашев Тимур",
        "nameOfRightFighter": "Федулов Игорь",
        "orderUID_left": 3239,
        "orderUID_right": 3241
    },
    {
        "TOURNAMENT_CATEGORIES_FK": 508,
        "VERTEX": 6,
        "categoryOfFighting": "63.5",
        "countOfRounds": "3",
        "countryOfLeftFighter": "Псковская",
        "countryOfRightFighter": "Республика Коми",
        "durationOfBreak": "60",
        "durationOfRound": "90",
        "fightId": 29,
        "nameOfLeftFighter": "Матвеев Даниил",
        "nameOfRightFighter": "Гуляев Тимофей",
        "orderUID_left": 3236,
        "orderUID_right": 3134
    },
    {
        "TOURNAMENT_CATEGORIES_FK": 508,
        "VERTEX": 5,
        "categoryOfFighting": "63.5",
        "countOfRounds": "3",
        "countryOfLeftFighter": "Псковская",
        "countryOfRightFighter": "Москва",
        "durationOfBreak": "60",
        "durationOfRound": "90",
        "fightId": 30,
        "nameOfLeftFighter": "Башин Игорь",
        "nameOfRightFighter": "Монахов Никита",
        "orderUID_left": 3237,
        "orderUID_right": 3186
    },
    {
        "TOURNAMENT_CATEGORIES_FK": 508,
        "VERTEX": 4,
        "categoryOfFighting": "63.5",
        "countOfRounds": "3",
        "countryOfLeftFighter": "Псковская",
        "countryOfRightFighter": "Санкт Петербург",
        "durationOfBreak": "60",
        "durationOfRound": "90",
        "fightId": 31,
        "nameOfLeftFighter": "Смирнов Олег",
        "nameOfRightFighter": "Утешев Ислам",
        "orderUID_left": 3238,
        "orderUID_right": 3240
    },
    {
        "TOURNAMENT_CATEGORIES_FK": 451,
        "VERTEX": 7,
        "categoryOfFighting": "67",
        "countOfRounds": "3",
        "countryOfLeftFighter": "Псковская",
        "countryOfRightFighter": "Удмуртская респ.",
        "durationOfBreak": "60",
        "durationOfRound": "90",
        "fightId": 32,
        "nameOfLeftFighter": "Куранов Артем",
        "nameOfRightFighter": "Газетдинов Артур",
        "orderUID_left": 3248,
        "orderUID_right": 3253
    },
    {
        "TOURNAMENT_CATEGORIES_FK": 451,
        "VERTEX": 6,
        "categoryOfFighting": "67",
        "countOfRounds": "3",
        "countryOfLeftFighter": "Псковская",
        "countryOfRightFighter": "Санкт Петербург",
        "durationOfBreak": "60",
        "durationOfRound": "90",
        "fightId": 33,
        "nameOfLeftFighter": "Лунев Кирилл",
        "nameOfRightFighter": "Асланов Аслан",
        "orderUID_left": 3150,
        "orderUID_right": 3252
    },
    {
        "TOURNAMENT_CATEGORIES_FK": 451,
        "VERTEX": 5,
        "categoryOfFighting": "67",
        "countOfRounds": "3",
        "countryOfLeftFighter": "Псковская",
        "countryOfRightFighter": "Москва",
        "durationOfBreak": "60",
        "durationOfRound": "90",
        "fightId": 34,
        "nameOfLeftFighter": "Гаврилов Руслан",
        "nameOfRightFighter": "Логвинов Олег",
        "orderUID_left": 3249,
        "orderUID_right": 3250
    },
    {
        "TOURNAMENT_CATEGORIES_FK": 451,
        "VERTEX": 4,
        "categoryOfFighting": "67",
        "countOfRounds": "3",
        "countryOfLeftFighter": "Псковская",
        "countryOfRightFighter": "КЧР",
        "durationOfBreak": "60",
        "durationOfRound": "90",
        "fightId": 35,
        "nameOfLeftFighter": "Поляков Александр",
        "nameOfRightFighter": "Уртенов Марат",
        "orderUID_left": 3162,
        "orderUID_right": 3251
    },
    {
        "TOURNAMENT_CATEGORIES_FK": 452,
        "VERTEX": 7,
        "categoryOfFighting": "71",
        "countOfRounds": "3",
        "countryOfLeftFighter": "Псковская",
        "countryOfRightFighter": "Санкт Петербург",
        "durationOfBreak": "60",
        "durationOfRound": "90",
        "fightId": 36,
        "nameOfLeftFighter": "Поляков Виктор",
        "nameOfRightFighter": "Магомедов Абдулхалык",
        "orderUID_left": 3163,
        "orderUID_right": 3243
    },
    {
        "TOURNAMENT_CATEGORIES_FK": 452,
        "VERTEX": 6,
        "categoryOfFighting": "71",
        "countOfRounds": "3",
        "countryOfLeftFighter": "Псковская",
        "countryOfRightFighter": "КЧР",
        "durationOfBreak": "60",
        "durationOfRound": "90",
        "fightId": 37,
        "nameOfLeftFighter": "Чулков Василий",
        "nameOfRightFighter": "Эсекуев  Шамиль",
        "orderUID_left": 3245,
        "orderUID_right": 3247
    },
    {
        "TOURNAMENT_CATEGORIES_FK": 452,
        "VERTEX": 5,
        "categoryOfFighting": "71",
        "countOfRounds": "3",
        "countryOfLeftFighter": "Псковская",
        "countryOfRightFighter": "Республика Коми",
        "durationOfBreak": "60",
        "durationOfRound": "90",
        "fightId": 38,
        "nameOfLeftFighter": "Зимбицкий Даниил",
        "nameOfRightFighter": "Мамедов Кирилл",
        "orderUID_left": 3244,
        "orderUID_right": 3133
    },
    {
        "TOURNAMENT_CATEGORIES_FK": 452,
        "VERTEX": 4,
        "categoryOfFighting": "71",
        "countOfRounds": "3",
        "countryOfLeftFighter": "Псковская",
        "countryOfRightFighter": "Санкт Петербург",
        "durationOfBreak": "60",
        "durationOfRound": "90",
        "fightId": 39,
        "nameOfLeftFighter": "Деменев Никита",
        "nameOfRightFighter": "Пантелеев Леонид",
        "orderUID_left": 3246,
        "orderUID_right": 3242
    },
    {
        "TOURNAMENT_CATEGORIES_FK": 569,
        "VERTEX": 1,
        "categoryOfFighting": "60",
        "countOfRounds": "3",
        "countryOfLeftFighter": "Москва",
        "countryOfRightFighter": "Минск",
        "durationOfBreak": "60",
        "durationOfRound": "120",
        "fightId": 40,
        "nameOfLeftFighter": "Удалкина  Юлия",
        "nameOfRightFighter": "Стребук  Наталья",
        "orderUID_left": 3197,
        "orderUID_right": 3077
    },
    {
        "TOURNAMENT_CATEGORIES_FK": 559,
        "VERTEX": 1,
        "categoryOfFighting": "63",
        "countOfRounds": "3",
        "countryOfLeftFighter": "Республика Коми",
        "countryOfRightFighter": "Минск",
        "durationOfBreak": "60",
        "durationOfRound": "120",
        "fightId": 41,
        "nameOfLeftFighter": "Ляшев Никита",
        "nameOfRightFighter": "Мелещик  Сергей",
        "orderUID_left": 3132,
        "orderUID_right": 3082
    },
    {
        "TOURNAMENT_CATEGORIES_FK": 570,
        "VERTEX": 1,
        "categoryOfFighting": "65",
        "countOfRounds": "3",
        "countryOfLeftFighter": "Москва",
        "countryOfRightFighter": "Минск",
        "durationOfBreak": "60",
        "durationOfRound": "120",
        "fightId": 42,
        "nameOfLeftFighter": "Булич Ясмина",
        "nameOfRightFighter": "Гришанович  Вера",
        "orderUID_left": 3183,
        "orderUID_right": 3088
    },
    {
        "TOURNAMENT_CATEGORIES_FK": 560,
        "VERTEX": 1,
        "categoryOfFighting": "69",
        "countOfRounds": "3",
        "countryOfLeftFighter": "Москва",
        "countryOfRightFighter": "Минск",
        "durationOfBreak": "60",
        "durationOfRound": "120",
        "fightId": 43,
        "nameOfLeftFighter": "Юрматов Бежан",
        "nameOfRightFighter": "Бандзеладзе  Давид",
        "orderUID_left": 3182,
        "orderUID_right": 3096
    },
    {
        "TOURNAMENT_CATEGORIES_FK": 494,
        "VERTEX": 7,
        "categoryOfFighting": "48",
        "countOfRounds": "3",
        "countryOfLeftFighter": "Псковская",
        "countryOfRightFighter": "Воронежская",
        "durationOfBreak": "60",
        "durationOfRound": "120",
        "fightId": 44,
        "nameOfLeftFighter": "Иванова Елена",
        "nameOfRightFighter": "Новоточинова Виктория",
        "orderUID_left": 3231,
        "orderUID_right": 3234
    },
    {
        "TOURNAMENT_CATEGORIES_FK": 494,
        "VERTEX": 6,
        "categoryOfFighting": "48",
        "countOfRounds": "3",
        "countryOfLeftFighter": "Псковская",
        "countryOfRightFighter": "Санкт Петербург",
        "durationOfBreak": "60",
        "durationOfRound": "120",
        "fightId": 45,
        "nameOfLeftFighter": "Сабурина Анастасия",
        "nameOfRightFighter": "Григорян Раиса",
        "orderUID_left": 3235,
        "orderUID_right": 3229
    },
    {
        "TOURNAMENT_CATEGORIES_FK": 494,
        "VERTEX": 5,
        "categoryOfFighting": "48",
        "countOfRounds": "3",
        "countryOfLeftFighter": "Псковская",
        "countryOfRightFighter": "Москва",
        "durationOfBreak": "60",
        "durationOfRound": "120",
        "fightId": 46,
        "nameOfLeftFighter": "Щелканова Ксения",
        "nameOfRightFighter": "Вахрушева Светлана",
        "orderUID_left": 3230,
        "orderUID_right": 3185
    },
    {
        "TOURNAMENT_CATEGORIES_FK": 494,
        "VERTEX": 4,
        "categoryOfFighting": "48",
        "countOfRounds": "3",
        "countryOfLeftFighter": "Псковская",
        "countryOfRightFighter": "Воронежская",
        "durationOfBreak": "60",
        "durationOfRound": "120",
        "fightId": 47,
        "nameOfLeftFighter": "Алиева Сания",
        "nameOfRightFighter": "Ермакова Евгения",
        "orderUID_left": 3232,
        "orderUID_right": 3233
    },
    {
        "TOURNAMENT_CATEGORIES_FK": 428,
        "VERTEX": 2,
        "categoryOfFighting": "63.5",
        "countOfRounds": "3",
        "countryOfLeftFighter": "Псковская",
        "countryOfRightFighter": "Минск",
        "durationOfBreak": "60",
        "durationOfRound": "120",
        "fightId": 48,
        "nameOfLeftFighter": "Яцинович  Александр",
        "nameOfRightFighter": "Мелещик  Сергей",
        "orderUID_left": 3167,
        "orderUID_right": 3103
    },
    {
        "TOURNAMENT_CATEGORIES_FK": 431,
        "VERTEX": 1,
        "categoryOfFighting": "75",
        "countOfRounds": "3",
        "countryOfLeftFighter": "Минск",
        "countryOfRightFighter": "Минск",
        "durationOfBreak": "60",
        "durationOfRound": "120",
        "fightId": 49,
        "nameOfLeftFighter": "Мирутко  Дмитрий",
        "nameOfRightFighter": "Кретов  Борис",
        "orderUID_left": 3110,
        "orderUID_right": 3106
    },
    {
        "TOURNAMENT_CATEGORIES_FK": 409,
        "VERTEX": 7,
        "categoryOfFighting": "63.5",
        "countOfRounds": "3",
        "countryOfLeftFighter": "Псковская",
        "countryOfRightFighter": "Санкт Петербург",
        "durationOfBreak": "60",
        "durationOfRound": "120",
        "fightId": 50,
        "nameOfLeftFighter": "Близнев Алексей",
        "nameOfRightFighter": "Магамедзаде Магамед",
        "orderUID_left": 3207,
        "orderUID_right": 3210
    },
    {
        "TOURNAMENT_CATEGORIES_FK": 409,
        "VERTEX": 6,
        "categoryOfFighting": "63.5",
        "countOfRounds": "3",
        "countryOfLeftFighter": "Псковская",
        "countryOfRightFighter": "КЧР",
        "durationOfBreak": "60",
        "durationOfRound": "120",
        "fightId": 51,
        "nameOfLeftFighter": "Алиев Фирдавс",
        "nameOfRightFighter": "Кочкаров Арсен",
        "orderUID_left": 3171,
        "orderUID_right": 3208
    },
    {
        "TOURNAMENT_CATEGORIES_FK": 409,
        "VERTEX": 5,
        "categoryOfFighting": "63.5",
        "countOfRounds": "3",
        "countryOfLeftFighter": "Псковская",
        "countryOfRightFighter": "Москва",
        "durationOfBreak": "60",
        "durationOfRound": "120",
        "fightId": 52,
        "nameOfLeftFighter": "Алексеев  Максим",
        "nameOfRightFighter": "Узун Георгий",
        "orderUID_left": 3166,
        "orderUID_right": 3180
    },
    {
        "TOURNAMENT_CATEGORIES_FK": 409,
        "VERTEX": 4,
        "categoryOfFighting": "63.5",
        "countOfRounds": "3",
        "countryOfLeftFighter": "Новгородская",
        "countryOfRightFighter": "Санкт Петербург",
        "durationOfBreak": "60",
        "durationOfRound": "120",
        "fightId": 53,
        "nameOfLeftFighter": "Белонович Ярослав",
        "nameOfRightFighter": "Черивмурзаев Абсамат",
        "orderUID_left": 3209,
        "orderUID_right": 3206
    },
    {
        "TOURNAMENT_CATEGORIES_FK": 410,
        "VERTEX": 1,
        "categoryOfFighting": "67",
        "countOfRounds": "3",
        "countryOfLeftFighter": "Псковская",
        "countryOfRightFighter": "Минск",
        "durationOfBreak": "60",
        "durationOfRound": "120",
        "fightId": 54,
        "nameOfLeftFighter": "Писцов Влад",
        "nameOfRightFighter": "Матюхин  Дмитрий",
        "orderUID_left": 3161,
        "orderUID_right": 3109
    },
    {
        "TOURNAMENT_CATEGORIES_FK": 469,
        "VERTEX": 7,
        "categoryOfFighting": "71",
        "countOfRounds": "3",
        "countryOfLeftFighter": "Псковская",
        "countryOfRightFighter": "КЧР",
        "durationOfBreak": "60",
        "durationOfRound": "120",
        "fightId": 55,
        "nameOfLeftFighter": "Умнов Владимир",
        "nameOfRightFighter": "Габараев  Амин",
        "orderUID_left": 3215,
        "orderUID_right": 3216
    },
    {
        "TOURNAMENT_CATEGORIES_FK": 469,
        "VERTEX": 6,
        "categoryOfFighting": "71",
        "countOfRounds": "3",
        "countryOfLeftFighter": "Новгородская",
        "countryOfRightFighter": "Санкт Петербург",
        "durationOfBreak": "60",
        "durationOfRound": "120",
        "fightId": 56,
        "nameOfLeftFighter": "Франевич  Александр",
        "nameOfRightFighter": "Таваев баймурза",
        "orderUID_left": 3104,
        "orderUID_right": 3214
    },
    {
        "TOURNAMENT_CATEGORIES_FK": 469,
        "VERTEX": 5,
        "categoryOfFighting": "71",
        "countOfRounds": "3",
        "countryOfLeftFighter": "Москва",
        "countryOfRightFighter": "Псковская",
        "durationOfBreak": "60",
        "durationOfRound": "120",
        "fightId": 57,
        "nameOfLeftFighter": "Мусаев Артур",
        "nameOfRightFighter": "Жирохов Виктор",
        "orderUID_left": 3181,
        "orderUID_right": 3211
    },
    {
        "TOURNAMENT_CATEGORIES_FK": 469,
        "VERTEX": 4,
        "categoryOfFighting": "71",
        "countOfRounds": "3",
        "countryOfLeftFighter": "Санкт Петербург",
        "countryOfRightFighter": "КЧР",
        "durationOfBreak": "60",
        "durationOfRound": "120",
        "fightId": 58,
        "nameOfLeftFighter": "Урбулатов Ергали",
        "nameOfRightFighter": "Узденов Джашарбек",
        "orderUID_left": 3212,
        "orderUID_right": 3213
    },
    {
        "TOURNAMENT_CATEGORIES_FK": 412,
        "VERTEX": 1,
        "categoryOfFighting": "75",
        "countOfRounds": "3",
        "countryOfLeftFighter": "Псковская",
        "countryOfRightFighter": "Псковская",
        "durationOfBreak": "60",
        "durationOfRound": "120",
        "fightId": 59,
        "nameOfLeftFighter": "Барсуков Владислав",
        "nameOfRightFighter": "Шарамков Владимир",
        "orderUID_left": 3172,
        "orderUID_right": 3164
    },
    {
        "TOURNAMENT_CATEGORIES_FK": 413,
        "VERTEX": 7,
        "categoryOfFighting": "81",
        "countOfRounds": "3",
        "countryOfLeftFighter": "Санкт Петербург",
        "countryOfRightFighter": "Псковская",
        "durationOfBreak": "60",
        "durationOfRound": "120",
        "fightId": 60,
        "nameOfLeftFighter": "Болтобаев Муроджон",
        "nameOfRightFighter": "Глазков Андрей",
        "orderUID_left": 3218,
        "orderUID_right": 3217
    },
    {
        "TOURNAMENT_CATEGORIES_FK": 413,
        "VERTEX": 6,
        "categoryOfFighting": "81",
        "countOfRounds": "3",
        "countryOfLeftFighter": "Псковская",
        "countryOfRightFighter": "Москва",
        "durationOfBreak": "60",
        "durationOfRound": "120",
        "fightId": 61,
        "nameOfLeftFighter": "Новиков Сергей",
        "nameOfRightFighter": "Зыков Артем",
        "orderUID_left": 3108,
        "orderUID_right": 3221
    },
    {
        "TOURNAMENT_CATEGORIES_FK": 413,
        "VERTEX": 5,
        "categoryOfFighting": "81",
        "countOfRounds": "3",
        "countryOfLeftFighter": "КЧР",
        "countryOfRightFighter": "Новгородская",
        "durationOfBreak": "60",
        "durationOfRound": "120",
        "fightId": 62,
        "nameOfLeftFighter": "Хасанов Рустам",
        "nameOfRightFighter": "Минханов Артур",
        "orderUID_left": 3222,
        "orderUID_right": 3220
    },
    {
        "TOURNAMENT_CATEGORIES_FK": 413,
        "VERTEX": 4,
        "categoryOfFighting": "81",
        "countOfRounds": "3",
        "countryOfLeftFighter": "Псковская",
        "countryOfRightFighter": "Санкт Петербург",
        "durationOfBreak": "60",
        "durationOfRound": "120",
        "fightId": 63,
        "nameOfLeftFighter": "Хабибуллин  Марат",
        "nameOfRightFighter": "Ашихмин Роман",
        "orderUID_left": 3159,
        "orderUID_right": 3219
    },
    {
        "TOURNAMENT_CATEGORIES_FK": 414,
        "VERTEX": 7,
        "categoryOfFighting": "86",
        "countOfRounds": "3",
        "countryOfLeftFighter": "Псковская",
        "countryOfRightFighter": "Москва",
        "durationOfBreak": "60",
        "durationOfRound": "120",
        "fightId": 64,
        "nameOfLeftFighter": "Андрусов Артем",
        "nameOfRightFighter": "Никитин Виталий",
        "orderUID_left": 3223,
        "orderUID_right": 3227
    },
    {
        "TOURNAMENT_CATEGORIES_FK": 414,
        "VERTEX": 6,
        "categoryOfFighting": "86",
        "countOfRounds": "3",
        "countryOfLeftFighter": "Псковская",
        "countryOfRightFighter": "Санкт Петербург",
        "durationOfBreak": "60",
        "durationOfRound": "120",
        "fightId": 65,
        "nameOfLeftFighter": "Косенков Виктор",
        "nameOfRightFighter": "Багатов  Вагид",
        "orderUID_left": 3224,
        "orderUID_right": 3111
    },
    {
        "TOURNAMENT_CATEGORIES_FK": 414,
        "VERTEX": 5,
        "categoryOfFighting": "86",
        "countOfRounds": "3",
        "countryOfLeftFighter": "Псковская",
        "countryOfRightFighter": "Новгородская",
        "durationOfBreak": "60",
        "durationOfRound": "120",
        "fightId": 66,
        "nameOfLeftFighter": "Жаворонков Иван",
        "nameOfRightFighter": "Костин Евгений",
        "orderUID_left": 3160,
        "orderUID_right": 3225
    },
    {
        "TOURNAMENT_CATEGORIES_FK": 414,
        "VERTEX": 4,
        "categoryOfFighting": "86",
        "countOfRounds": "3",
        "countryOfLeftFighter": "КЧР",
        "countryOfRightFighter": "Санкт Петербург",
        "durationOfBreak": "60",
        "durationOfRound": "120",
        "fightId": 67,
        "nameOfLeftFighter": "Блимготов Темирлан",
        "nameOfRightFighter": "Иванов Максим",
        "orderUID_left": 3226,
        "orderUID_right": 3228
    },
    {
        "TOURNAMENT_CATEGORIES_FK": 473,
        "VERTEX": 7,
        "categoryOfFighting": "91",
        "countOfRounds": "3",
        "countryOfLeftFighter": "Псковская",
        "countryOfRightFighter": "Москва",
        "durationOfBreak": "60",
        "durationOfRound": "120",
        "fightId": 68,
        "nameOfLeftFighter": "Ветров Алексей",
        "nameOfRightFighter": "Герасимов Антон",
        "orderUID_left": 3094,
        "orderUID_right": 3138
    },
    {
        "TOURNAMENT_CATEGORIES_FK": 473,
        "VERTEX": 6,
        "categoryOfFighting": "91",
        "countOfRounds": "3",
        "countryOfLeftFighter": "Санкт Петербург",
        "countryOfRightFighter": "КЧР",
        "durationOfBreak": "60",
        "durationOfRound": "120",
        "fightId": 69,
        "nameOfLeftFighter": "Шаоев Муаед",
        "nameOfRightFighter": "Халкечев  Аликбек",
        "orderUID_left": 3105,
        "orderUID_right": 3205
    },
    {
        "TOURNAMENT_CATEGORIES_FK": 473,
        "VERTEX": 5,
        "categoryOfFighting": "91",
        "countOfRounds": "3",
        "countryOfLeftFighter": "Московская",
        "countryOfRightFighter": "Санкт Петербург",
        "durationOfBreak": "60",
        "durationOfRound": "120",
        "fightId": 70,
        "nameOfLeftFighter": "Крюков Алексей",
        "nameOfRightFighter": "Гогочури Алик",
        "orderUID_left": 3140,
        "orderUID_right": 3204
    },
    {
        "TOURNAMENT_CATEGORIES_FK": 473,
        "VERTEX": 4,
        "categoryOfFighting": "91",
        "countOfRounds": "3",
        "countryOfLeftFighter": "Московская",
        "countryOfRightFighter": "Псковская",
        "durationOfBreak": "60",
        "durationOfRound": "120",
        "fightId": 71,
        "nameOfLeftFighter": "Мордвинов Григорий",
        "nameOfRightFighter": "Татьянченко Павел",
        "orderUID_left": 3139,
        "orderUID_right": 3202
    },
    {
        "TOURNAMENT_CATEGORIES_FK": 416,
        "VERTEX": 1,
        "categoryOfFighting": "100000",
        "countOfRounds": "3",
        "countryOfLeftFighter": "Псковская",
        "countryOfRightFighter": "Минск",
        "durationOfBreak": "60",
        "durationOfRound": "120",
        "fightId": 72,
        "nameOfLeftFighter": "Туголуков Виктор",
        "nameOfRightFighter": "Захар  Дмитрий",
        "orderUID_left": 3176,
        "orderUID_right": 3112
    },
    {
        "TOURNAMENT_CATEGORIES_FK": 546,
        "VERTEX": 1,
        "categoryOfFighting": "74",
        "countOfRounds": "3",
        "countryOfLeftFighter": "Минск",
        "countryOfRightFighter": "Минск",
        "durationOfBreak": "60",
        "durationOfRound": "120",
        "fightId": 73,
        "nameOfLeftFighter": "Пуздров  Михаил",
        "nameOfRightFighter": "Франевич  Александр",
        "orderUID_left": 3083,
        "orderUID_right": 3086
    }
]
